[{"strm":2657,"crseId":351256,"crseOfferNbr":1,"subject":"NEPAL","catalogNbr":"1102","titleShort":"Elementary Nepali II","titleLong":"Elementary Nepali II","enrollGroups":[{"classSections":[{"ssrComponent":"LEC","ssrComponentLong":"Lecture","section":"001","classNbr":6199,"meetings":[{"classMtgNbr":1,"timeStart":"01:25PM","timeEnd":"02:15PM","startDt":"01/25/2017","endDt":"05/10/2017","instructors":[{"instrAssignSeq":1,"netid":"so15","firstName":"Shambhu","middleName":"","lastName":"Oja"}],"pattern":"MWRF","facilityDescr":"Rockefeller Hall 339","bldgDescr":"Rockefeller Hall","facilityDescrshort":"RCK339","meetingTopicDescription":""},{"classMtgNbr":2,"timeStart":"02:30PM","timeEnd":"03:20PM","startDt":"01/25/2017","endDt":"05/10/2017","instructors":[],"pattern":"T","facilityDescr":"Rockefeller Hall 339","bldgDescr":"Rockefeller Hall","facilityDescrshort":"RCK339","meetingTopicDescription":""}],"notes":[{"classNotesSeq":1,"descrlong":"Prerequisite:  NEPAL 1101 or placement by examination."}],"campus":"MAIN","campusDescr":"Ithaca","location":"ITH","locationDescr":"Ithaca, NY (Main Campus)","startDt":"01/25/2017","endDt":"05/10/2017","addConsent":"N","addConsentDescr":"No Special Consent Required","isComponentGraded":true,"instructionMode":"P","instrModeDescrshort":"In Person","instrModeDescr":"In Person","topicDescription":""}],"unitsMinimum":6,"unitsMaximum":6,"componentsOptional":[],"componentsRequired":["LEC"],"gradingBasis":"GRI","gradingBasisShort":"GradeNoAud","gradingBasisLong":"Letter grades only (no audit)","simpleCombinations":[],"sessionCode":"1","sessionBeginDt":"01/25/2017","sessionEndDt":"05/10/2017","sessionLong":"Regular Academic Session"}],"description":"Intended for beginners. The emphasis is on basic grammar, speaking, and comprehension skills, using culturally appropriate materials and texts. Devanagari script for reading and writing is also introduced.","catalogBreadth":"","catalogDistr":"","catalogLang":"","catalogForbiddenOverlaps":"","catalogAttribute":"","catalogWhenOffered":"Fall, spring.","catalogComments":"","catalogPrereqCoreq":"Prerequisite: NEPAL 1101 or examination.","catalogFee":"","catalogSatisfiesReq":"","catalogPermission":"","catalogCourseSubfield":"","catalogOutcomes":null,"acadCareer":"UG","acadGroup":"AS"},{"strm":2657,"crseId":351258,"crseOfferNbr":1,"subject":"NEPAL","catalogNbr":"2202","titleShort":"Intermed Nepali Convrstn II","titleLong":"Intermediate Nepali Conversation II","enrollGroups":[{"classSections":[{"ssrComponent":"LEC","ssrComponentLong":"Lecture","section":"001","classNbr":6200,"meetings":[{"classMtgNbr":1,"timeStart":"08:40AM","timeEnd":"09:55AM","startDt":"01/25/2017","endDt":"05/10/2017","instructors":[{"instrAssignSeq":1,"netid":"so15","firstName":"Shambhu","middleName":"","lastName":"Oja"}],"pattern":"MW","facilityDescr":"Rockefeller Hall 339","bldgDescr":"Rockefeller Hall","facilityDescrshort":"RCK339","meetingTopicDescription":""}],"notes":[{"classNotesSeq":1,"descrlong":"Prerequisite:  NEPAL 2201 or placement by examination."}],"campus":"MAIN","campusDescr":"Ithaca","location":"ITH","locationDescr":"Ithaca, NY (Main Campus)","startDt":"01/25/2017","endDt":"05/10/2017","addConsent":"N","addConsentDescr":"No Special Consent Required","isComponentGraded":true,"instructionMode":"P","instrModeDescrshort":"In Person","instrModeDescr":"In Person","topicDescription":""}],"unitsMinimum":3,"unitsMaximum":3,"componentsOptional":[],"componentsRequired":["LEC"],"gradingBasis":"GRI","gradingBasisShort":"GradeNoAud","gradingBasisLong":"Letter grades only (no audit)","simpleCombinations":[],"sessionCode":"1","sessionBeginDt":"01/25/2017","sessionEndDt":"05/10/2017","sessionLong":"Regular Academic Session"}],"description":"Intermediate instruction in spoken grammar and verbal comprehension skills, with special attention to developing technical vocabularies and other verbal skills appropriate to students' professional fields.","catalogBreadth":"(GB)","catalogDistr":"","catalogLang":"Satisfies Option 1.","catalogForbiddenOverlaps":"","catalogAttribute":"","catalogWhenOffered":"Spring, summer.","catalogComments":"","catalogPrereqCoreq":"Prerequisite: NEPAL 2201 or examination.","catalogFee":"","catalogSatisfiesReq":"","catalogPermission":"","catalogCourseSubfield":"","catalogOutcomes":null,"acadCareer":"UG","acadGroup":"AS"},{"strm":2657,"crseId":351260,"crseOfferNbr":1,"subject":"NEPAL","catalogNbr":"2204","titleShort":"Intermed Nepali Compos II","titleLong":"Intermediate Nepali Composition II","enrollGroups":[{"classSections":[{"ssrComponent":"LEC","ssrComponentLong":"Lecture","section":"001","classNbr":6201,"meetings":[{"classMtgNbr":1,"timeStart":"10:30AM","timeEnd":"12:00PM","startDt":"01/25/2017","endDt":"05/10/2017","instructors":[{"instrAssignSeq":1,"netid":"so15","firstName":"Shambhu","middleName":"","lastName":"Oja"}],"pattern":"TR","facilityDescr":"Rockefeller Hall 339","bldgDescr":"Rockefeller Hall","facilityDescrshort":"RCK339","meetingTopicDescription":""}],"notes":[{"classNotesSeq":1,"descrlong":"Prerequisite:  NEPAL 2203 or placement by examination."}],"campus":"MAIN","campusDescr":"Ithaca","location":"ITH","locationDescr":"Ithaca, NY (Main Campus)","startDt":"01/25/2017","endDt":"05/10/2017","addConsent":"N","addConsentDescr":"No Special Consent Required","isComponentGraded":true,"instructionMode":"P","instrModeDescrshort":"In Person","instrModeDescr":"In Person","topicDescription":""}],"unitsMinimum":3,"unitsMaximum":3,"componentsOptional":[],"componentsRequired":["LEC"],"gradingBasis":"GRI","gradingBasisShort":"GradeNoAud","gradingBasisLong":"Letter grades only (no audit)","simpleCombinations":[],"sessionCode":"1","sessionBeginDt":"01/25/2017","sessionEndDt":"05/10/2017","sessionLong":"Regular Academic Session"}],"description":"Systematic review of written grammar and reading comprehension, with special attention to the technical vocabularies, necessary writing skills, and published materials typical of advanced students' professional fields.","catalogBreadth":"(GB)","catalogDistr":"","catalogLang":"Satisfies Option 1.","catalogForbiddenOverlaps":"","catalogAttribute":"","catalogWhenOffered":"Spring, summer.","catalogComments":"","catalogPrereqCoreq":"Prerequisite: NEPAL 2203 or examination.","catalogFee":"","catalogSatisfiesReq":"","catalogPermission":"","catalogCourseSubfield":"","catalogOutcomes":null,"acadCareer":"UG","acadGroup":"AS"},{"strm":2657,"crseId":351263,"crseOfferNbr":1,"subject":"NEPAL","catalogNbr":"3302","titleShort":"Advanced Nepali II","titleLong":"Advanced Nepali II","enrollGroups":[{"classSections":[{"ssrComponent":"LEC","ssrComponentLong":"Lecture","section":"001","classNbr":6202,"meetings":[{"classMtgNbr":1,"timeStart":"12:20PM","timeEnd":"01:10PM","startDt":"01/25/2017","endDt":"05/10/2017","instructors":[{"instrAssignSeq":1,"netid":"so15","firstName":"Shambhu","middleName":"","lastName":"Oja"}],"pattern":"MWF","facilityDescr":"Rockefeller Hall 339","bldgDescr":"Rockefeller Hall","facilityDescrshort":"RCK339","meetingTopicDescription":""}],"notes":[{"classNotesSeq":1,"descrlong":"Prerequisite: NEPAL 2204, 3301 or permission of instructor."}],"campus":"MAIN","campusDescr":"Ithaca","location":"ITH","locationDescr":"Ithaca, NY (Main Campus)","startDt":"01/25/2017","endDt":"05/10/2017","addConsent":"N","addConsentDescr":"No Special Consent Required","isComponentGraded":true,"instructionMode":"P","instrModeDescrshort":"In Person","instrModeDescr":"In Person","topicDescription":""}],"unitsMinimum":3,"unitsMaximum":3,"componentsOptional":[],"componentsRequired":["LEC"],"gradingBasis":"GRI","gradingBasisShort":"GradeNoAud","gradingBasisLong":"Letter grades only (no audit)","simpleCombinations":[],"sessionCode":"1","sessionBeginDt":"01/25/2017","sessionEndDt":"05/10/2017","sessionLong":"Regular Academic Session"}],"description":"Reading of advanced texts, together with advanced drill on the spoken language.","catalogBreadth":"(GB)","catalogDistr":"","catalogLang":"Satisfies Option 1.","catalogForbiddenOverlaps":"","catalogAttribute":"","catalogWhenOffered":"Spring, summer.","catalogComments":"","catalogPrereqCoreq":"Prerequisite: NEPAL 3301 or permission of instructor.","catalogFee":"","catalogSatisfiesReq":"","catalogPermission":"","catalogCourseSubfield":"","catalogOutcomes":null,"acadCareer":"UG","acadGroup":"AS"}]