[{"strm":2664,"crseId":363875,"crseOfferNbr":1,"subject":"VTBMS","catalogNbr":"1200","titleShort":"Vet Med: Science and Practice","titleLong":"Veterinary Medicine: Science and Practice","enrollGroups":[{"classSections":[{"ssrComponent":"LEC","ssrComponentLong":"Lecture","section":"001","classNbr":1266,"meetings":[{"classMtgNbr":1,"timeStart":"09:00AM","timeEnd":"12:00PM","startDt":"06/26/2017","endDt":"07/14/2017","instructors":[],"pattern":"MTWRF","facilityDescr":"To Be Assigned","bldgDescr":null,"facilityDescrshort":null,"meetingTopicDescription":""}],"notes":[{"classNotesSeq":1,"descrlong":"This Summer Session class is offered by the School of Continuing Education and Summer Sessions. For details visit http://www.sce.cornell.edu/ss/courses/courses.php?v=2646."}],"campus":"MAIN","campusDescr":"Ithaca","location":"ITH","locationDescr":"Ithaca, NY (Main Campus)","startDt":"06/26/2017","endDt":"07/14/2017","addConsent":"N","addConsentDescr":"No Special Consent Required","isComponentGraded":true,"instructionMode":"P","instrModeDescrshort":"In Person","instrModeDescr":"In Person","topicDescription":""},{"ssrComponent":"LAB","ssrComponentLong":"Laboratory","section":"401","classNbr":1268,"meetings":[{"classMtgNbr":1,"timeStart":"01:30PM","timeEnd":"03:30PM","startDt":"06/26/2017","endDt":"07/14/2017","instructors":[],"pattern":"MTWRF","facilityDescr":"To Be Assigned","bldgDescr":null,"facilityDescrshort":null,"meetingTopicDescription":""}],"notes":[],"campus":"MAIN","campusDescr":"Ithaca","location":"ITH","locationDescr":"Ithaca, NY (Main Campus)","startDt":"06/26/2017","endDt":"07/14/2017","addConsent":"N","addConsentDescr":"No Special Consent Required","isComponentGraded":false,"instructionMode":"P","instrModeDescrshort":"In Person","instrModeDescr":"In Person","topicDescription":""}],"unitsMinimum":3,"unitsMaximum":3,"componentsOptional":[],"componentsRequired":["LEC","LAB"],"gradingBasis":"GRD","gradingBasisShort":"Graded","gradingBasisLong":"Letter grades only","simpleCombinations":[],"sessionCode":"SP2","sessionBeginDt":"05/31/2017","sessionEndDt":"08/08/2017","sessionLong":"Summer Special Session 2"}],"description":"The course serves as an introduction to the science and practice of veterinary medicine. Aspects of the anatomy, physiology, pharmacology and several clinical specialties will provide insight into the knowledge behind veterinary medicine and other medical careers. Material will also offer insight into the diversity of career options available in this and related fields. Study will be at the level of introductory undergraduate course material.","catalogBreadth":"","catalogDistr":"","catalogLang":"","catalogForbiddenOverlaps":"","catalogAttribute":"","catalogWhenOffered":"Summer.","catalogComments":"","catalogPrereqCoreq":"","catalogFee":"","catalogSatisfiesReq":"","catalogPermission":"","catalogCourseSubfield":"","catalogOutcomes":null,"acadCareer":"UG","acadGroup":"VM"}]